daemon_application/__init__.py
daemon_application/app.py
daemon_application/base.py
daemon_application-2.0.0.dist-info/LICENSE
daemon_application-2.0.0.dist-info/METADATA
daemon_application-2.0.0.dist-info/WHEEL
daemon_application-2.0.0.dist-info/top_level.txt
daemon_application-2.0.0.dist-info/RECORD
