Metadata-Version: 2.1
Name: daemon-application
Version: 2.0.0
Summary: A simple python package for creating daemon applications.
Author: Zhao ZhiPeng
Author-email: zhaozhipeng@zencore.cn
Maintainer: Zhao ZhiPeng
Maintainer-email: zhaozhipeng@zencore.cn
License: MIT
Keywords: daemon-application
Classifier: Development Status :: 5 - Production/Stable
Classifier: Intended Audience :: Developers
Classifier: Topic :: Software Development :: Libraries :: Python Modules
Classifier: License :: OSI Approved :: MIT License
Classifier: Programming Language :: Python :: 3
Classifier: Programming Language :: Python :: 3 :: Only
Requires-Python: >=2.7, !=3.2.0
License-File: LICENSE
Requires-Dist: six
Requires-Dist: zenutils >=0.3.16
Requires-Dist: psutil ==5.9.0 ; python_version == "2.6"
Requires-Dist: PyYAML ==5.4.1 ; python_version == "2.7"
Requires-Dist: psutil ; python_version == "2.7"
Requires-Dist: click ; python_version == "2.7"
Requires-Dist: PyYAML ==3.11 ; python_version == "3.2"
Requires-Dist: psutil ==5.4.3 ; python_version == "3.2"
Requires-Dist: click ==3.3 ; python_version == "3.2"
Requires-Dist: PyYAML ==3.11 ; python_version == "3.3"
Requires-Dist: PyYAML ==5.2 ; python_version == "3.4"
Requires-Dist: click ; python_version > "3.2"
Requires-Dist: PyYAML ; python_version > "3.4"
Requires-Dist: psutil ; python_version >= "3.3"
